resourceComponents/__init__.py
resourceComponents/bastion_hosts.py
resourceComponents/bootstrap.py
resourceComponents/cloudwatch.py
resourceComponents/elastic_container.py
resourceComponents/iam_helpers.py
resourceComponents/lambda_function.py
resourceComponents/load_balancer.py
resourceComponents/memorydb_redis.py
resourceComponents/rabbitmq_broker.py
resourceComponents/rds_cluster.py
resourceComponents/rds_instance.py
resourceComponents/redshift_cluster.py
resourceComponents/route53.py
resourceComponents/s3_buckets.py
resourceComponents/secrets_manager.py
resourceComponents/security_group.py
resourceComponents/subnet_distributor.py
resourceComponents/vpc.py
resources/__init__.py
resources/autoscaling.py
resources/aws_lambda.py
resources/cloudwatch.py
resources/ec2.py
resources/ecs.py
resources/kms.py
resources/lb.py
resources/memorydb.py
resources/mq.py
resources/random.py
resources/rds.py
resources/redshift.py
resources/route53.py
resources/s3.py
resources/sm.py
xangobolt_pulumi_aws-1.8.7.dist-info/LICENSE
xangobolt_pulumi_aws-1.8.7.dist-info/METADATA
xangobolt_pulumi_aws-1.8.7.dist-info/WHEEL
xangobolt_pulumi_aws-1.8.7.dist-info/top_level.txt
xangobolt_pulumi_aws-1.8.7.dist-info/RECORD
