Metadata-Version: 2.1
Name: xangobolt-pulumi-aws
Version: 1.8.7
Summary: Pulumi modules python package for AWS infrastructure as code
Home-page: https://github.com/pypa/sampleproject
Author: xangobolt
Author-email: samson.adewale@xangobolt.com
Project-URL: Bug Tracker, https://github.com/pypa/sampleproject/issues
Classifier: Programming Language :: Python :: 3
Classifier: License :: OSI Approved :: MIT License
Classifier: Operating System :: OS Independent
Requires-Python: >=3.9
License-File: LICENSE
